flask_bootstrap_module_extendeds/__init__.py
flask_bootstrap_module_extendeds/_backwards.py
flask_bootstrap_module_extendeds/_compat.py
flask_bootstrap_module_extendeds/actions.py
flask_bootstrap_module_extendeds/babel.py
flask_bootstrap_module_extendeds/base.py
flask_bootstrap_module_extendeds/cli.py
flask_bootstrap_module_extendeds/consts.py
flask_bootstrap_module_extendeds/forms.py
flask_bootstrap_module_extendeds/helpers.py
flask_bootstrap_module_extendeds/menu.py
flask_bootstrap_module_extendeds/nav.py
flask_bootstrap_module_extendeds/refusion.py
flask_bootstrap_module_extendeds/tools.py
flask_bootstrap_module_extendeds/static/jquery.js
flask_bootstrap_module_extendeds/static/jquery.min.js
flask_bootstrap_module_extendeds/static/jquery.min.map
flask_bootstrap_module_extendeds/static/css/bootstrap-theme.css
flask_bootstrap_module_extendeds/static/css/bootstrap-theme.css.map
flask_bootstrap_module_extendeds/static/css/bootstrap-theme.min.css
flask_bootstrap_module_extendeds/static/css/bootstrap.css
flask_bootstrap_module_extendeds/static/css/bootstrap.css.map
flask_bootstrap_module_extendeds/static/css/bootstrap.min.css
flask_bootstrap_module_extendeds/static/fonts/glyphicons-halflings-regular.eot
flask_bootstrap_module_extendeds/static/fonts/glyphicons-halflings-regular.svg
flask_bootstrap_module_extendeds/static/fonts/glyphicons-halflings-regular.ttf
flask_bootstrap_module_extendeds/static/fonts/glyphicons-halflings-regular.woff
flask_bootstrap_module_extendeds/static/fonts/glyphicons-halflings-regular.woff2
flask_bootstrap_module_extendeds/static/js/bootstrap.js
flask_bootstrap_module_extendeds/static/js/bootstrap.min.js
flask_bootstrap_module_extendeds/static/js/npm.js
flask_bootstrap_module_extendeds/templates/aioflask/README
flask_bootstrap_module_extendeds/templates/aioflask/alembic.ini.mako
flask_bootstrap_module_extendeds/templates/aioflask/env.py
flask_bootstrap_module_extendeds/templates/aioflask/script.py.mako
flask_bootstrap_module_extendeds-5.1.6.dist-info/METADATA
flask_bootstrap_module_extendeds-5.1.6.dist-info/WHEEL
flask_bootstrap_module_extendeds-5.1.6.dist-info/top_level.txt
flask_bootstrap_module_extendeds-5.1.6.dist-info/RECORD
